{
  "mode": "pre",
  "tag": "next",
  "initialVersions": {
    "@swisspost/design-system-changelog-github": "1.0.2",
    "@swisspost/design-system-components": "8.2.0",
    "@swisspost/design-system-components-angular-workspace": "1.1.9",
    "@swisspost/design-system-components-angular": "8.2.0",
    "@swisspost/design-system-components-react": "8.2.0",
    "@swisspost/design-system-demo": "8.0.2",
    "@swisspost/design-system-documentation": "5.4.0",
    "@swisspost/design-system-icons": "8.2.0",
    "@swisspost/internet-header": "1.14.5",
    "@swisspost/design-system-intranet-header-workspace": "3.0.21",
    "@swisspost/design-system-intranet-header": "8.2.0",
    "@swisspost/design-system-intranet-header-showcase": "1.0.9",
    "@swisspost/design-system-migrations": "8.2.0",
    "@swisspost/design-system-nextjs-integration": "0.1.13",
    "@swisspost/design-system-styles": "8.2.0",
    "@swisspost/design-system-styles-primeng-workspace": "1.0.5",
    "@swisspost/design-system-styles-primeng": "8.2.0",
    "@swisspost/design-system-tokens": "8.2.0"
  },
  "changesets": [
    "2024-10-17-update-icons",
    "2024-10-27-update-icons",
    "2024-11-10-update-icons",
    "2024-11-17-update-icons",
    "2025-01-17-update-icons",
    "angry-bulldogs-refuse",
    "angry-eagles-appear",
    "beige-jobs-do",
    "big-frogs-admire",
    "big-hats-clap",
    "big-maps-pay",
    "big-socks-dress",
    "blue-kings-beg",
    "brave-kings-dance",
    "breezy-cups-add",
    "breezy-poets-shout",
    "bright-coins-repeat",
    "bright-insects-unite",
    "brown-badgers-dream",
    "calm-rabbits-pull",
    "chatty-kiwis-travel",
    "chatty-pigs-hear",
    "chatty-spoons-unite",
    "chilled-owls-walk",
    "chilly-carrots-explain",
    "clean-icons-complain",
    "clean-windows-think",
    "clever-cheetahs-draw",
    "cold-baboons-appear",
    "cold-bags-chew",
    "cold-panthers-vanish",
    "cuddly-bears-check",
    "cuddly-gifts-film",
    "curly-insects-breathe",
    "curvy-sheep-help",
    "cyan-days-kiss",
    "cyan-years-pretend",
    "dirty-mayflies-taste",
    "dirty-squids-hunt",
    "dry-moons-walk",
    "dry-trainers-stare",
    "dull-actors-collect",
    "dull-falcons-hope",
    "early-baboons-cross",
    "early-knives-own",
    "eight-turkeys-matter",
    "eighty-bees-invent",
    "eighty-ghosts-explain",
    "eleven-keys-work",
    "empty-islands-kneel",
    "fair-actors-scream",
    "fair-llamas-battle",
    "famous-panthers-bow",
    "fast-bats-poke",
    "fast-fans-wash",
    "few-ways-beam",
    "fifty-dodos-wait",
    "fifty-students-call",
    "five-hornets-sin",
    "flat-badgers-fly",
    "flat-bears-tap",
    "four-beers-leave",
    "four-jokes-tease",
    "fresh-files-crash",
    "fresh-schools-peel",
    "friendly-impalas-reflect",
    "friendly-insects-breathe",
    "funny-knives-rule",
    "funny-shrimps-care",
    "giant-games-swim",
    "gold-chairs-grin",
    "gold-chefs-rule",
    "gold-dryers-drop",
    "gold-news-repair",
    "gold-news-retire",
    "good-pens-play",
    "good-pets-eat",
    "good-spoons-tie",
    "good-wombats-jam",
    "gorgeous-flowers-flow",
    "gorgeous-glasses-end",
    "gorgeous-needles-run",
    "great-humans-talk",
    "grumpy-lobsters-agree",
    "grumpy-parrots-wonder",
    "happy-needles-repeat",
    "heavy-eyes-live",
    "heavy-rats-explode",
    "hip-gifts-give",
    "honest-numbers-end",
    "hot-lizards-dance",
    "hungry-balloons-sin",
    "hungry-penguins-turn",
    "itchy-meals-drum",
    "khaki-cougars-itch",
    "kind-buses-trade",
    "kind-papayas-provide",
    "large-gorillas-hope",
    "large-hornets-complain",
    "late-days-approve",
    "lazy-gorillas-admire",
    "lemon-clocks-clean",
    "long-shrimps-roll",
    "loud-dingos-remember",
    "loud-peaches-hang",
    "lovely-cooks-serve",
    "lovely-deers-itch",
    "lovely-mails-clap",
    "lovely-mirrors-travel",
    "lucky-grapes-wink",
    "metal-geese-swim",
    "metal-pens-explode",
    "metal-rivers-look",
    "modern-pumpkins-kneel",
    "moody-coats-kneel",
    "nasty-ads-greet",
    "neat-jars-destroy",
    "neat-suits-provide",
    "nervous-lizards-laugh",
    "nervous-rocks-shop",
    "new-cougars-count",
    "new-goats-impress",
    "new-pianos-mix",
    "nice-beans-impress",
    "nice-cycles-provide",
    "nice-ligers-attend",
    "nine-baboons-rule",
    "nine-rocks-carry",
    "ninety-nails-float",
    "old-spiders-travel",
    "olive-squids-enjoy",
    "orange-maps-tan",
    "pink-weeks-relate",
    "plenty-apricots-raise",
    "plenty-taxis-hear",
    "poor-jars-call",
    "poor-laws-impress",
    "popular-games-rush",
    "popular-mirrors-cross",
    "proud-actors-knock",
    "proud-cheetahs-act",
    "proud-moons-impress",
    "purple-impalas-own",
    "purple-terms-march",
    "quick-buses-give",
    "quick-eagles-watch",
    "quick-mails-joke",
    "quiet-apes-rhyme",
    "quiet-dolls-lick",
    "quiet-pots-tickle",
    "rare-dryers-count",
    "real-gorillas-behave",
    "real-phones-scream",
    "red-cobras-cry",
    "red-comics-cough",
    "red-lies-lick",
    "red-moose-do",
    "rich-timers-listen",
    "rotten-bats-look",
    "rude-needles-matter",
    "rude-shrimps-wonder",
    "selfish-bats-run",
    "selfish-ways-know",
    "serious-chefs-exercise",
    "shaggy-experts-give",
    "sharp-baboons-smile",
    "sharp-bobcats-grab",
    "sharp-crews-watch",
    "shiny-ears-care",
    "short-olives-sleep",
    "shy-walls-exercise",
    "silent-ears-drive",
    "silent-vans-care",
    "silver-coins-invent",
    "six-roses-flow",
    "six-spiders-smoke",
    "sixty-clouds-cough",
    "sixty-items-promise",
    "slimy-plums-sniff",
    "slimy-rockets-pull",
    "slow-fishes-reply",
    "smart-cobras-train",
    "smooth-bugs-explode",
    "smooth-spoons-matter",
    "soft-moles-whisper",
    "soft-pugs-dream",
    "spicy-pumpkins-grab",
    "spotty-shoes-film",
    "stale-guests-love",
    "strange-bottles-impress",
    "strange-mice-bake",
    "stupid-walls-tie",
    "tame-terms-push",
    "tasty-beans-knock",
    "tender-laws-confess",
    "thirty-cats-juggle",
    "thirty-chairs-suffer",
    "thirty-mirrors-thank",
    "three-lies-do",
    "three-zoos-listen",
    "tidy-dolls-walk",
    "tidy-keys-push",
    "tidy-paws-type",
    "tiny-socks-count",
    "tough-cheetahs-clean",
    "tough-dancers-attend",
    "tricky-crews-agree",
    "twelve-dodos-breathe",
    "twenty-chairs-kick",
    "twenty-fans-prove",
    "twenty-items-drum",
    "violet-geckos-shave",
    "violet-jokes-stare",
    "violet-poems-attend",
    "warm-drinks-prove",
    "warm-walls-stare",
    "weak-falcons-study",
    "weak-jars-rhyme",
    "wicked-scissors-buy",
    "wild-bugs-work",
    "wise-hornets-happen",
    "wise-rats-whisper",
    "wise-spies-shave",
    "wise-tomatoes-brake",
    "yellow-garlics-draw",
    "yellow-gifts-sit",
    "yellow-yaks-jog"
  ]
}
